xyz_py/__init__.py
xyz_py/atomic.py
xyz_py/cli.py
xyz_py/version.py
xyz_py/xyz_py.py
xyz_py-5.19.2.dist-info/licenses/LICENSE
xyz_py-5.19.2.dist-info/METADATA
xyz_py-5.19.2.dist-info/WHEEL
xyz_py-5.19.2.dist-info/entry_points.txt
xyz_py-5.19.2.dist-info/top_level.txt
xyz_py-5.19.2.dist-info/RECORD
