Metadata-Version: 2.4
Name: xyz_py
Version: 5.19.2
Summary: A package for manipulating xyz files and chemical structures
Home-page: https://gitlab.com/jonkragskow/xyz_py
Author: Jon Kragskow
Author-email: jonkragskow@gmail.com
License: GPL-3.0-or-later
Project-URL: Bug Tracker, https://gitlab.com/jonkragskow/xyz_py/-/issues
Project-URL: Documentation, https://jonkragskow.gitlab.io/xyz_py
Classifier: Programming Language :: Python :: 3
Classifier: Operating System :: OS Independent
Requires-Python: >=3.6
License-File: LICENSE
Requires-Dist: numpy
Requires-Dist: ase
Dynamic: author
Dynamic: author-email
Dynamic: classifier
Dynamic: description
Dynamic: description-content-type
Dynamic: home-page
Dynamic: license
Dynamic: license-file
Dynamic: project-url
Dynamic: requires-dist
Dynamic: requires-python
Dynamic: summary
